{"account":{"uid":"py1q1fz3_yz0l_9gle_8w06_fy4n89mfmkjo","nickname":"2","account":"2","password":"2","registerTime":1715889024712,"lastLoginTime":1716230787273,"lastOnlineTime":1716230829108},"base":{"signedInTime":0,"coin":500,"vcoin":0,"vigor":86400,"jingJie":1,"cengJi":1,"exp":0,"moHe":0,"moBi":0,"spiritStones":0,"title":0,"society":0,"sect":0,"soul":0,"gemScore":0,"citta":{},"skill":[5000],"usingSkill":[5000,5000,5000,5000,5000]},"offline":null,"friend":{"friend":[]},"body":{"weapon":null,"helmet":null,"necklace":null,"clothes":null,"ring":null,"trousers":null,"amulet":null,"shoes":null,"mount":null,"hiddenWeeapon":null,"fashion":null,"magicWeapon":null,"weaponGems":[],"helmetGems":[],"necklaceGems":[],"clothesGems":[],"ringGems":[],"trousersGems":[],"amuletGems":[],"shoesGems":[]},"bag":{"collect":[],"equipment":[],"gem":[],"prop":[],"material":[],"book":[],"other":[]},"battle":{"battleSpeed":1,"level":{},"copy":{"usedMap":{}},"secret":{"usedMap":{}},"boss":{"lastChallengeTime":{}},"gather":{"startTimeMap":{"10001":1716230286,"10002":null,"10003":1716230758},"gatherTimeMap":{"10001":3600,"10002":null,"10003":3600}}}}