{"account":{"uid":"o16g5cat-nehz-4pjn-9s2q-qg8qdvu5wkft","nickname":"1","account":"2","password":"1","registerTime":1693411480210,"lastLoginTime":1711373522372,"lastOnlineTime":1711373998523},"base":{"signedInTime":0,"coin":9999929930006914,"vcoin":0,"vigor":86400,"jingJie":29,"cengJi":10,"exp":128102534300,"moHe":0,"moBi":0,"spiritStones":0,"title":0,"society":0,"sect":0,"soul":0,"gemScore":0,"citta":{},"skill":[5000],"usingSkill":[5000,5000,5000,5000,5000]},"offline":null,"friend":{"friend":[]},"body":{"weapon":{"id":40040,"uid":"15ptg9r97i1g","star":10,"level":0,"mingKe":0,"shenYou":0,"mainAttri":[1],"wuXingAttri":[16,17,18],"secondAttri":[1,8],"bodyAttri":[26]},"helmet":null,"necklace":null,"clothes":null,"ring":null,"trousers":null,"amulet":null,"shoes":null,"mount":{"id":49996,"uid":"dck6ud4oou6","star":9,"level":0,"mingKe":0,"shenYou":0,"mainAttri":[],"wuXingAttri":[],"secondAttri":[1,8,10],"bodyAttri":[5,6,26]},"hiddenWeeapon":null,"fashion":null,"magicWeapon":null,"weaponGems":[],"helmetGems":[],"necklaceGems":[],"clothesGems":[],"ringGems":[],"trousersGems":[],"amuletGems":[],"shoesGems":[]},"bag":{"collect":[],"equipment":[["id","uid","star","level","mingKe","shenYou","mainAttri","wuXingAttri","secondAttri","bodyAttri"],[40056,"1uckekgifrv8",2,0,0,0,[1],[14,15,16,17],[1,8,10],[5,26]],[40064,"42444m9gne7",7,0,0,0,[1],[14,17],[1,8,10],[4]],[40040,"hm082a7kclo",11,0,0,0,[1],[15,16,17,18],[1,8,10],[4,5,26]],[40056,"br4jemeigbs",12,0,0,0,[1],[15,17],[1,8,10],[4,7]],[40064,"3ir56njmk9a",2,0,0,0,[1],[15,16,17],[1,8,10],[4,5,6,7,26]],[49996,"6pehp0qja7g",2,0,0,0,[],[],[10],[4,5,6,7,26]]],"gem":[],"prop":[["id","count"],[2017,449202378],[2016,1]],"material":[],"book":[],"other":[]},"battle":{"level":{},"copy":{"usedMap":null},"secret":{"usedMap":null},"boss":{"lastChallengeTime":null},"gather":{"usedMap":null,"startTimeMap":null,"gatherTimeMap":null}}}